.testr.conf
.travis.yml
AUTHORS
ChangeLog
LICENSE
README.rst
TODO
announce.rst
requirements.txt
setup.cfg
setup.py
test-requirements.txt
tox.ini
docs/Makefile
docs/source/command_ref.rst
docs/source/conf.py
docs/source/faq.rst
docs/source/history.rst
docs/source/index.rst
docs/source/quickstart.rst
docs/source/server.rst
docs/source/screenshots/call_graph.png
docs/source/screenshots/file_contents.png
docs/source/screenshots/file_list.png
docs/source/screenshots/run_details.png
docs/source/screenshots/runs.png
docs/source/screenshots/stats.png
smiley/__init__.py
smiley/app.py
smiley/db.py
smiley/db_linecache.py
smiley/jsonutil.py
smiley/listener.py
smiley/local.py
smiley/output.py
smiley/processor.py
smiley/publisher.py
smiley/schema.sql
smiley/stats.py
smiley/tracer.py
smiley/util.py
smiley/uuidstack.py
smiley.egg-info/PKG-INFO
smiley.egg-info/SOURCES.txt
smiley.egg-info/dependency_links.txt
smiley.egg-info/entry_points.txt
smiley.egg-info/requires.txt
smiley.egg-info/top_level.txt
smiley.egg-info/zip-safe
smiley/commands/__init__.py
smiley/commands/export.py
smiley/commands/list.py
smiley/commands/listen_cmd.py
smiley/commands/monitor.py
smiley/commands/record.py
smiley/commands/replay.py
smiley/commands/report.py
smiley/commands/run.py
smiley/commands/server.py
smiley/commands/show.py
smiley/commands/stats.py
smiley/commands/threads.py
smiley/presentation/__init__.py
smiley/presentation/pagination.py
smiley/presentation/stats.py
smiley/presentation/syntax.py
smiley/presentation/trace.py
smiley/report/__init__.py
smiley/report/html.py
smiley/report/static/css/bootstrap-responsive.css
smiley/report/static/css/bootstrap-responsive.min.css
smiley/report/static/css/bootstrap-theme.css
smiley/report/static/css/bootstrap-theme.min.css
smiley/report/static/css/bootstrap.css
smiley/report/static/css/bootstrap.min.css
smiley/report/static/css/pygments.css
smiley/report/static/css/run.css
smiley/report/static/css/stats.css
smiley/report/static/fonts/glyphicons-halflings-regular.eot
smiley/report/static/fonts/glyphicons-halflings-regular.svg
smiley/report/static/fonts/glyphicons-halflings-regular.ttf
smiley/report/static/fonts/glyphicons-halflings-regular.woff
