Metadata-Version: 1.1
Name: smiley
Version: 0.7.0
Summary: Smiley spies on your Python app while it runs
Home-page: https://smiley.readthedocs.org/
Author: Doug Hellmann
Author-email: doug@doughellmann.com
License: Apache-2
Keywords: debugger
Platform: UNKNOWN
Classifier: Development Status :: 3 - Alpha
Classifier: Environment :: Console
Classifier: Intended Audience :: Developers
Classifier: Intended Audience :: Information Technology
Classifier: License :: OSI Approved :: Apache Software License
Classifier: Operating System :: OS Independent
Classifier: Programming Language :: Python
Classifier: Programming Language :: Python :: 2
Classifier: Programming Language :: Python :: 2.7
